mkdtoc/__init__.py
mkdtoc/mkdtoc.py
mkdtoc-0.1.0.dist-info/entry_points.txt
mkdtoc-0.1.0.dist-info/WHEEL
mkdtoc-0.1.0.dist-info/METADATA
mkdtoc-0.1.0.dist-info/RECORD
